{"nodes": [{"id": "c_users_ieq3q_carvver_src_components_dashboard_pages_freelancer_order_detail_jsx", "label": "freelancer_order_detail.jsx", "file_type": "code", "source_file": "C:\\Users\\ieq3q\\carvver\\src\\components\\Dashboard\\pages\\freelancer_order_detail.jsx", "source_location": "L1"}, {"id": "freelancer_order_detail_inlinestatus", "label": "InlineStatus()", "file_type": "code", "source_file": "C:\\Users\\ieq3q\\carvver\\src\\components\\Dashboard\\pages\\freelancer_order_detail.jsx", "source_location": "L32"}, {"id": "freelancer_order_detail_formatfulfillmentlabel", "label": "formatFulfillmentLabel()", "file_type": "code", "source_file": "C:\\Users\\ieq3q\\carvver\\src\\components\\Dashboard\\pages\\freelancer_order_detail.jsx", "source_location": "L37"}, {"id": "freelancer_order_detail_formatpayoutstate", "label": "formatPayoutState()", "file_type": "code", "source_file": "C:\\Users\\ieq3q\\carvver\\src\\components\\Dashboard\\pages\\freelancer_order_detail.jsx", "source_location": "L43"}, {"id": "freelancer_order_detail_buildaccepteddeliveryassettypes", "label": "buildAcceptedDeliveryAssetTypes()", "file_type": "code", "source_file": "C:\\Users\\ieq3q\\carvver\\src\\components\\Dashboard\\pages\\freelancer_order_detail.jsx", "source_location": "L54"}, {"id": "freelancer_order_detail_deliveryassetlist", "label": "DeliveryAssetList()", "file_type": "code", "source_file": "C:\\Users\\ieq3q\\carvver\\src\\components\\Dashboard\\pages\\freelancer_order_detail.jsx", "source_location": "L62"}, {"id": "freelancer_order_detail_deliveryhistory", "label": "DeliveryHistory()", "file_type": "code", "source_file": "C:\\Users\\ieq3q\\carvver\\src\\components\\Dashboard\\pages\\freelancer_order_detail.jsx", "source_location": "L99"}, {"id": "freelancer_order_detail_freelancerorderdetail", "label": "FreelancerOrderDetail()", "file_type": "code", "source_file": "C:\\Users\\ieq3q\\carvver\\src\\components\\Dashboard\\pages\\freelancer_order_detail.jsx", "source_location": "L210"}], "edges": [{"source": "c_users_ieq3q_carvver_src_components_dashboard_pages_freelancer_order_detail_jsx", "target": "react", "relation": "imports_from", "confidence": "EXTRACTED", "source_file": "C:\\Users\\ieq3q\\carvver\\src\\components\\Dashboard\\pages\\freelancer_order_detail.jsx", "source_location": "L1", "weight": 1.0}, {"source": "c_users_ieq3q_carvver_src_components_dashboard_pages_freelancer_order_detail_jsx", "target": "framer_motion", "relation": "imports_from", "confidence": "EXTRACTED", "source_file": "C:\\Users\\ieq3q\\carvver\\src\\components\\Dashboard\\pages\\freelancer_order_detail.jsx", "source_location": "L2", "weight": 1.0}, {"source": "c_users_ieq3q_carvver_src_components_dashboard_pages_freelancer_order_detail_jsx", "target": "lucide_react", "relation": "imports_from", "confidence": "EXTRACTED", "source_file": "C:\\Users\\ieq3q\\carvver\\src\\components\\Dashboard\\pages\\freelancer_order_detail.jsx", "source_location": "L3", "weight": 1.0}, {"source": "c_users_ieq3q_carvver_src_components_dashboard_pages_freelancer_order_detail_jsx", "target": "react_router_dom", "relation": "imports_from", "confidence": "EXTRACTED", "source_file": "C:\\Users\\ieq3q\\carvver\\src\\components\\Dashboard\\pages\\freelancer_order_detail.jsx", "source_location": "L4", "weight": 1.0}, {"source": "c_users_ieq3q_carvver_src_components_dashboard_pages_freelancer_order_detail_jsx", "target": "c_users_ieq3q_carvver_src_components_dashboard_pages_profile_css", "relation": "imports_from", "confidence": "EXTRACTED", "source_file": "C:\\Users\\ieq3q\\carvver\\src\\components\\Dashboard\\pages\\freelancer_order_detail.jsx", "source_location": "L5", "weight": 1.0}, {"source": "c_users_ieq3q_carvver_src_components_dashboard_pages_freelancer_order_detail_jsx", "target": "c_users_ieq3q_carvver_src_components_dashboard_pages_workflow_pages_css", "relation": "imports_from", "confidence": "EXTRACTED", "source_file": "C:\\Users\\ieq3q\\carvver\\src\\components\\Dashboard\\pages\\freelancer_order_detail.jsx", "source_location": "L6", "weight": 1.0}, {"source": "c_users_ieq3q_carvver_src_components_dashboard_pages_freelancer_order_detail_jsx", "target": "c_users_ieq3q_carvver_src_components_dashboard_shared_customerprofileshared", "relation": "imports_from", "confidence": "EXTRACTED", "source_file": "C:\\Users\\ieq3q\\carvver\\src\\components\\Dashboard\\pages\\freelancer_order_detail.jsx", "source_location": "L7", "weight": 1.0}, {"source": "c_users_ieq3q_carvver_src_components_dashboard_pages_freelancer_order_detail_jsx", "target": "c_users_ieq3q_carvver_src_components_dashboard_shared_customerprofileconfig", "relation": "imports_from", "confidence": "EXTRACTED", "source_file": "C:\\Users\\ieq3q\\carvver\\src\\components\\Dashboard\\pages\\freelancer_order_detail.jsx", "source_location": "L14", "weight": 1.0}, {"source": "c_users_ieq3q_carvver_src_components_dashboard_pages_freelancer_order_detail_jsx", "target": "c_users_ieq3q_carvver_src_components_dashboard_hooks_usemarketplaceworkflow", "relation": "imports_from", "confidence": "EXTRACTED", "source_file": "C:\\Users\\ieq3q\\carvver\\src\\components\\Dashboard\\pages\\freelancer_order_detail.jsx", "source_location": "L15", "weight": 1.0}, {"source": "c_users_ieq3q_carvver_src_components_dashboard_pages_freelancer_order_detail_jsx", "target": "c_users_ieq3q_carvver_src_components_shared_searchable_combobox", "relation": "imports_from", "confidence": "EXTRACTED", "source_file": "C:\\Users\\ieq3q\\carvver\\src\\components\\Dashboard\\pages\\freelancer_order_detail.jsx", "source_location": "L24", "weight": 1.0}, {"source": "c_users_ieq3q_carvver_src_components_dashboard_pages_freelancer_order_detail_jsx", "target": "freelancer_order_detail_inlinestatus", "relation": "contains", "confidence": "EXTRACTED", "source_file": "C:\\Users\\ieq3q\\carvver\\src\\components\\Dashboard\\pages\\freelancer_order_detail.jsx", "source_location": "L32", "weight": 1.0}, {"source": "c_users_ieq3q_carvver_src_components_dashboard_pages_freelancer_order_detail_jsx", "target": "freelancer_order_detail_formatfulfillmentlabel", "relation": "contains", "confidence": "EXTRACTED", "source_file": "C:\\Users\\ieq3q\\carvver\\src\\components\\Dashboard\\pages\\freelancer_order_detail.jsx", "source_location": "L37", "weight": 1.0}, {"source": "c_users_ieq3q_carvver_src_components_dashboard_pages_freelancer_order_detail_jsx", "target": "freelancer_order_detail_formatpayoutstate", "relation": "contains", "confidence": "EXTRACTED", "source_file": "C:\\Users\\ieq3q\\carvver\\src\\components\\Dashboard\\pages\\freelancer_order_detail.jsx", "source_location": "L43", "weight": 1.0}, {"source": "c_users_ieq3q_carvver_src_components_dashboard_pages_freelancer_order_detail_jsx", "target": "freelancer_order_detail_buildaccepteddeliveryassettypes", "relation": "contains", "confidence": "EXTRACTED", "source_file": "C:\\Users\\ieq3q\\carvver\\src\\components\\Dashboard\\pages\\freelancer_order_detail.jsx", "source_location": "L54", "weight": 1.0}, {"source": "c_users_ieq3q_carvver_src_components_dashboard_pages_freelancer_order_detail_jsx", "target": "freelancer_order_detail_deliveryassetlist", "relation": "contains", "confidence": "EXTRACTED", "source_file": "C:\\Users\\ieq3q\\carvver\\src\\components\\Dashboard\\pages\\freelancer_order_detail.jsx", "source_location": "L62", "weight": 1.0}, {"source": "c_users_ieq3q_carvver_src_components_dashboard_pages_freelancer_order_detail_jsx", "target": "freelancer_order_detail_deliveryhistory", "relation": "contains", "confidence": "EXTRACTED", "source_file": "C:\\Users\\ieq3q\\carvver\\src\\components\\Dashboard\\pages\\freelancer_order_detail.jsx", "source_location": "L99", "weight": 1.0}, {"source": "c_users_ieq3q_carvver_src_components_dashboard_pages_freelancer_order_detail_jsx", "target": "freelancer_order_detail_freelancerorderdetail", "relation": "contains", "confidence": "EXTRACTED", "source_file": "C:\\Users\\ieq3q\\carvver\\src\\components\\Dashboard\\pages\\freelancer_order_detail.jsx", "source_location": "L210", "weight": 1.0}, {"source": "freelancer_order_detail_freelancerorderdetail", "target": "freelancer_order_detail_formatpayoutstate", "relation": "calls", "confidence": "EXTRACTED", "source_file": "C:\\Users\\ieq3q\\carvver\\src\\components\\Dashboard\\pages\\freelancer_order_detail.jsx", "source_location": "L438", "weight": 1.0}, {"source": "freelancer_order_detail_freelancerorderdetail", "target": "freelancer_order_detail_formatfulfillmentlabel", "relation": "calls", "confidence": "EXTRACTED", "source_file": "C:\\Users\\ieq3q\\carvver\\src\\components\\Dashboard\\pages\\freelancer_order_detail.jsx", "source_location": "L444", "weight": 1.0}, {"source": "freelancer_order_detail_freelancerorderdetail", "target": "freelancer_order_detail_buildaccepteddeliveryassettypes", "relation": "calls", "confidence": "EXTRACTED", "source_file": "C:\\Users\\ieq3q\\carvver\\src\\components\\Dashboard\\pages\\freelancer_order_detail.jsx", "source_location": "L533", "weight": 1.0}], "raw_calls": [{"caller_nid": "freelancer_order_detail_formatfulfillmentlabel", "callee": "toLowerCase", "source_file": "C:\\Users\\ieq3q\\carvver\\src\\components\\Dashboard\\pages\\freelancer_order_detail.jsx", "source_location": "L38"}, {"caller_nid": "freelancer_order_detail_formatfulfillmentlabel", "callee": "trim", "source_file": "C:\\Users\\ieq3q\\carvver\\src\\components\\Dashboard\\pages\\freelancer_order_detail.jsx", "source_location": "L38"}, {"caller_nid": "freelancer_order_detail_formatfulfillmentlabel", "callee": "String", "source_file": "C:\\Users\\ieq3q\\carvver\\src\\components\\Dashboard\\pages\\freelancer_order_detail.jsx", "source_location": "L38"}, {"caller_nid": "freelancer_order_detail_formatpayoutstate", "callee": "toLowerCase", "source_file": "C:\\Users\\ieq3q\\carvver\\src\\components\\Dashboard\\pages\\freelancer_order_detail.jsx", "source_location": "L44"}, {"caller_nid": "freelancer_order_detail_formatpayoutstate", "callee": "trim", "source_file": "C:\\Users\\ieq3q\\carvver\\src\\components\\Dashboard\\pages\\freelancer_order_detail.jsx", "source_location": "L44"}, {"caller_nid": "freelancer_order_detail_formatpayoutstate", "callee": "String", "source_file": "C:\\Users\\ieq3q\\carvver\\src\\components\\Dashboard\\pages\\freelancer_order_detail.jsx", "source_location": "L44"}, {"caller_nid": "freelancer_order_detail_buildaccepteddeliveryassettypes", "callee": "join", "source_file": "C:\\Users\\ieq3q\\carvver\\src\\components\\Dashboard\\pages\\freelancer_order_detail.jsx", "source_location": "L55"}, {"caller_nid": "freelancer_order_detail_deliveryassetlist", "callee": "map", "source_file": "C:\\Users\\ieq3q\\carvver\\src\\components\\Dashboard\\pages\\freelancer_order_detail.jsx", "source_location": "L67"}, {"caller_nid": "freelancer_order_detail_deliveryhistory", "callee": "map", "source_file": "C:\\Users\\ieq3q\\carvver\\src\\components\\Dashboard\\pages\\freelancer_order_detail.jsx", "source_location": "L113"}, {"caller_nid": "freelancer_order_detail_freelancerorderdetail", "callee": "useNavigate", "source_file": "C:\\Users\\ieq3q\\carvver\\src\\components\\Dashboard\\pages\\freelancer_order_detail.jsx", "source_location": "L211"}, {"caller_nid": "freelancer_order_detail_freelancerorderdetail", "callee": "useParams", "source_file": "C:\\Users\\ieq3q\\carvver\\src\\components\\Dashboard\\pages\\freelancer_order_detail.jsx", "source_location": "L212"}, {"caller_nid": "freelancer_order_detail_freelancerorderdetail", "callee": "useRef", "source_file": "C:\\Users\\ieq3q\\carvver\\src\\components\\Dashboard\\pages\\freelancer_order_detail.jsx", "source_location": "L213"}, {"caller_nid": "freelancer_order_detail_freelancerorderdetail", "callee": "useState", "source_file": "C:\\Users\\ieq3q\\carvver\\src\\components\\Dashboard\\pages\\freelancer_order_detail.jsx", "source_location": "L214"}, {"caller_nid": "freelancer_order_detail_freelancerorderdetail", "callee": "useState", "source_file": "C:\\Users\\ieq3q\\carvver\\src\\components\\Dashboard\\pages\\freelancer_order_detail.jsx", "source_location": "L215"}, {"caller_nid": "freelancer_order_detail_freelancerorderdetail", "callee": "useState", "source_file": "C:\\Users\\ieq3q\\carvver\\src\\components\\Dashboard\\pages\\freelancer_order_detail.jsx", "source_location": "L216"}, {"caller_nid": "freelancer_order_detail_freelancerorderdetail", "callee": "useState", "source_file": "C:\\Users\\ieq3q\\carvver\\src\\components\\Dashboard\\pages\\freelancer_order_detail.jsx", "source_location": "L217"}, {"caller_nid": "freelancer_order_detail_freelancerorderdetail", "callee": "useState", "source_file": "C:\\Users\\ieq3q\\carvver\\src\\components\\Dashboard\\pages\\freelancer_order_detail.jsx", "source_location": "L222"}, {"caller_nid": "freelancer_order_detail_freelancerorderdetail", "callee": "useState", "source_file": "C:\\Users\\ieq3q\\carvver\\src\\components\\Dashboard\\pages\\freelancer_order_detail.jsx", "source_location": "L232"}, {"caller_nid": "freelancer_order_detail_freelancerorderdetail", "callee": "useState", "source_file": "C:\\Users\\ieq3q\\carvver\\src\\components\\Dashboard\\pages\\freelancer_order_detail.jsx", "source_location": "L233"}, {"caller_nid": "freelancer_order_detail_freelancerorderdetail", "callee": "useState", "source_file": "C:\\Users\\ieq3q\\carvver\\src\\components\\Dashboard\\pages\\freelancer_order_detail.jsx", "source_location": "L234"}, {"caller_nid": "freelancer_order_detail_freelancerorderdetail", "callee": "useEffect", "source_file": "C:\\Users\\ieq3q\\carvver\\src\\components\\Dashboard\\pages\\freelancer_order_detail.jsx", "source_location": "L254"}, {"caller_nid": "freelancer_order_detail_freelancerorderdetail", "callee": "useEffect", "source_file": "C:\\Users\\ieq3q\\carvver\\src\\components\\Dashboard\\pages\\freelancer_order_detail.jsx", "source_location": "L258"}, {"caller_nid": "freelancer_order_detail_freelancerorderdetail", "callee": "useEffect", "source_file": "C:\\Users\\ieq3q\\carvver\\src\\components\\Dashboard\\pages\\freelancer_order_detail.jsx", "source_location": "L262"}, {"caller_nid": "freelancer_order_detail_freelancerorderdetail", "callee": "map", "source_file": "C:\\Users\\ieq3q\\carvver\\src\\components\\Dashboard\\pages\\freelancer_order_detail.jsx", "source_location": "L544"}, {"caller_nid": "freelancer_order_detail_freelancerorderdetail", "callee": "map", "source_file": "C:\\Users\\ieq3q\\carvver\\src\\components\\Dashboard\\pages\\freelancer_order_detail.jsx", "source_location": "L810"}]}